opendp/__init__.py
opendp/_convert.py
opendp/_data.py
opendp/_internal.py
opendp/_lib.py
opendp/accuracy.py
opendp/combinators.py
opendp/context.py
opendp/core.py
opendp/domains.py
opendp/measurements.py
opendp/measures.py
opendp/metrics.py
opendp/mod.py
opendp/prelude.py
opendp/py.typed
opendp/transformations.py
opendp/typing.py
opendp/extras/__init__.py
opendp/extras/_utilities.py
opendp/extras/examples/__init__.py
opendp/extras/mbi/__init__.py
opendp/extras/mbi/_aim/__init__.py
opendp/extras/mbi/_fixed/__init__.py
opendp/extras/mbi/_mst/__init__.py
opendp/extras/mbi/_sequential/__init__.py
opendp/extras/mbi/_table/__init__.py
opendp/extras/mbi/_utilities/__init__.py
opendp/extras/numpy/__init__.py
opendp/extras/numpy/canonical.py
opendp/extras/numpy/_make_np_clamp/__init__.py
opendp/extras/numpy/_make_np_count/__init__.py
opendp/extras/numpy/_make_np_mean/__init__.py
opendp/extras/numpy/_make_np_sscp/__init__.py
opendp/extras/numpy/_make_np_sum/__init__.py
opendp/extras/polars/__init__.py
opendp/extras/polars/contingency_table.py
opendp/extras/sklearn/__init__.py
opendp/extras/sklearn/_make_eigendecomposition/__init__.py
opendp/extras/sklearn/_make_eigenvalues/__init__.py
opendp/extras/sklearn/_make_eigenvector/__init__.py
opendp/extras/sklearn/decomposition/__init__.py
opendp/extras/sklearn/linear_model/__init__.py
opendp/extras/sklearn/linear_model/_make_private_theil_sen/__init__.py
opendp/lib/opendp.abi3.so
opendp-0.14.1.dist-info/METADATA
opendp-0.14.1.dist-info/WHEEL
opendp-0.14.1.dist-info/top_level.txt
opendp-0.14.1.dist-info/RECORD
opendp-0.14.1.dist-info/licenses/LICENSE
